{
    "mcmeal at mcdonalds (or equivalent combo meal)": "快餐价格",
    "domestic beer (0.5 liter draught)": "白酒价格",
    "water (1.5 liter bottle)": "水费",
    "cappuccino (regular)": "奶茶价格",
    "apartment (1 bedroom) in city centre": "城区房价",
    "apartment (1 bedroom) outside of centre": "乡镇房价",
    "basic (electricity, heating, cooling, water, garbage) for 85m2 apartment": "公共设施",
    "internet (60 mbps or more, unlimited data, cable/adsl)": "网费",
    "fitness club, monthly fee for 1 adult": "健身成本",
    "average monthly net salary (after tax)": "薪水",
    "cost of living index": "生活成本",
    "purchasing power index": "购买力",
    "safety index": "安全系数",
    "health care index": "医保",
    "pollution index": "污染情况",
    "logged gdp per capita": "人均GDP",
    "social support": "社保",
    "healthy life expectancy": "预期寿命",
    "freedom to make life choices": "社会自由度",
    "generosity": "社会关爱程度",
    "perceptions of corruption": "腐败度",
    "population": "人口",
    "employment": "就业率",
    "startup": "创业氛围",
    "tourism": "旅游情况",
    "housing": "住房状况",
    "transport": "交通设施",
    "health": "卫生系统",
    "food": "食品供应",
    "internet speed": "网速",
    "access to contraception": "避孕方法",
    "gender equality": "性别问题",
    "immigration tolerance": "移民容忍度",
    "lgbt friendly": "同性恋友好度",
    "nightscene": "景色",
    "beer": "啤酒价格",
    "festival": "节日情况",
    "avgtemperature": "平均气温"
}